.gitignore
.travis.yml
COPYING
MANIFEST.in
Makefile
NEWS
README.md
setup.py
test.py
nosetests_/settings.py
nosetests_/test_acl.py
nosetests_/test_auth.py
nosetests_/test_context.py
nosetests_/test_dir.py
nosetests_/test_file.py
pysmbc.egg-info/PKG-INFO
pysmbc.egg-info/SOURCES.txt
pysmbc.egg-info/dependency_links.txt
pysmbc.egg-info/top_level.txt
smbc/__init__.py
smbc/context.c
smbc/context.h
smbc/dir.c
smbc/dir.h
smbc/file.c
smbc/file.h
smbc/smbcdirent.c
smbc/smbcdirent.h
smbc/smbcmodule.c
smbc/smbcmodule.h
smbc/xattr.py
tests/__init__.py
tests/conftest.py
tests/test_acl.py
tests/test_auth.py
tests/test_dir.py