Metadata-Version: 1.1
Name: pysmbc
Version: 1.0.25.1
Summary: Python bindings for libsmbclient
Home-page: https://github.com/hamano/pysmbc
Author: ['Tim Waugh <twaugh@redhat.com>', 'Tsukasa Hamano <hamano@osstech.co.jp>', 'Roberto Polli <rpolli@babel.it>']
Author-email: UNKNOWN
License: GPLv2+
Platform: UNKNOWN
Classifier: Intended Audience :: Developers
Classifier: Topic :: Software Development :: Libraries :: Python Modules
Classifier: License :: OSI Approved :: GNU General Public License (GPL)
Classifier: Development Status :: 5 - Production/Stable
Classifier: Operating System :: Unix
Classifier: Programming Language :: C
